python_thingset/__init__.py
python_thingset/cli.py
python_thingset/client.py
python_thingset/id.py
python_thingset/log.py
python_thingset/response.py
python_thingset/thingset.py
python_thingset/backends/__init__.py
python_thingset/backends/backend.py
python_thingset/backends/can.py
python_thingset/backends/serial.py
python_thingset/backends/socket.py
python_thingset/encoders/__init__.py
python_thingset/encoders/binary.py
python_thingset/encoders/text.py
python_thingset-0.2.6.dist-info/METADATA
python_thingset-0.2.6.dist-info/WHEEL
python_thingset-0.2.6.dist-info/entry_points.txt
python_thingset-0.2.6.dist-info/licenses/LICENSE
python_thingset-0.2.6.dist-info/RECORD
