Metadata-Version: 2.4
Name: python_thingset
Version: 0.2.6
Summary: A Python library for ThingSet functionality
Project-URL: homepage, https://pypi.org/project/python-thingset/
Project-URL: repository, https://github.com/Brill-Power/python-thingset
Project-URL: documentation, https://python-thingset.readthedocs.io/en/latest/
Author-email: Adam Mitchell <adam.mitchell@brillpower.com>
License-Expression: Apache-2.0
License-File: LICENSE
Classifier: Operating System :: OS Independent
Classifier: Programming Language :: Python :: 3
Requires-Python: >=3.10
Requires-Dist: can-isotp==2.0.6
Requires-Dist: cbor2==5.6.5
Requires-Dist: pyserial==3.5
Requires-Dist: python-can==4.5.0
Provides-Extra: dev
Requires-Dist: pytest-cov==5.0.0; extra == 'dev'
Requires-Dist: pytest==8.3.5; extra == 'dev'
Requires-Dist: ruff==0.6.7; extra == 'dev'
